{
    "title": "CONTACT 2 Template",
    "description": "เทมเพลตฟอร์มติดต่อ 2",
    "category": "contact",
    "preview": "https://standard.wpdevs.co/wp-content/uploads/2025/05/IMG-CONTACT-001.png",
    "tags": ["modern", "business"],
    
    "content":[{"id":"57bd433a","settings":{"padding":{"unit":"px","top":"0","right":"0","bottom":"0","left":"0","isLinked":true},"margin":{"unit":"px","top":"20","right":"0","bottom":"0","left":"0","isLinked":false}},"elements":[{"id":"1fc781f2","settings":{"content_width":"full","border_border":"solid","border_width":{"unit":"px","top":"0","right":"0","bottom":"1","left":"0","isLinked":false},"border_color":"#DBDBDB","margin":{"unit":"px","top":"0","right":"0","bottom":"0","left":"0","isLinked":true},"padding":{"unit":"px","top":"0","right":"0","bottom":"8","left":"0","isLinked":false}},"elements":[{"id":"10ff6f80","settings":{"title":"\u0e15\u0e34\u0e14\u0e15\u0e48\u0e2d\u0e2b\u0e19\u0e48\u0e27\u0e22\u0e07\u0e32\u0e19","header_size":"h1","_margin":{"unit":"px","top":"0","right":"0","bottom":"-9","left":"0","isLinked":false},"_padding":{"unit":"px","top":"0","right":"0","bottom":"10","left":"0","isLinked":false},"_flex_align_self":"flex-start","_border_border":"solid","_border_width":{"unit":"px","top":"0","right":"0","bottom":"4","left":"0","isLinked":false},"_border_color":"#FD8100","__dynamic__":[]},"elements":[],"isInner":false,"widgetType":"heading","elType":"widget"}],"isInner":true,"elType":"container"}],"isInner":false,"elType":"container"},{"id":"5c7752e2","settings":{"flex_direction":"row","flex_gap":{"unit":"px","size":0,"column":"0","row":"0","isLinked":true},"margin":{"unit":"px","top":"30","right":"0","bottom":"50","left":"0","isLinked":false},"padding":{"unit":"px","top":"0","right":"0","bottom":"0","left":"0","isLinked":false}},"elements":[{"id":"6f1328cb","settings":{"flex_direction":"column","content_width":"full","width":{"unit":"%","size":"50"}},"elements":[{"id":"6397929d","settings":{"shortcode":"[department_contact]"},"elements":[],"isInner":false,"widgetType":"shortcode","elType":"widget"}],"isInner":true,"elType":"container"},{"id":"384f538a","settings":{"flex_direction":"column","content_width":"full","width":{"unit":"%","size":"50"}},"elements":[{"id":"55f6164e","settings":{"address":"\u0e0a\u0e31\u0e49\u0e19 4, \u0e2d\u0e32\u0e04\u0e32\u0e23\u0e2a\u0e16\u0e32\u0e1a\u0e31\u0e19\u0e40\u0e1e\u0e37\u0e48\u0e2d\u0e01\u0e32\u0e23\u0e22\u0e38\u0e15\u0e34\u0e18\u0e23\u0e23\u0e21\u0e41\u0e2b\u0e48\u0e07\u0e1b\u0e23\u0e30\u0e40\u0e17\u0e28\u0e44\u0e17\u0e22 (TIJ, \u0e40\u0e25\u0e02\u0e17\u0e35\u0e48 999 Chaeng Watthana Rd, Thung Song Hong, Lak Si, Bangkok 10210","zoom":{"unit":"px","size":13,"sizes":[]},"height":{"unit":"px","size":445,"sizes":[]},"_border_radius":{"unit":"px","top":"8","right":"8","bottom":"8","left":"8","isLinked":true}},"elements":[],"isInner":false,"widgetType":"google_maps","elType":"widget"},{"id":"3d65528d","settings":{"title":"\u0e2a\u0e33\u0e19\u0e31\u0e01\u0e07\u0e32\u0e19\u0e1e\u0e31\u0e12\u0e19\u0e32\u0e23\u0e31\u0e10\u0e1a\u0e32\u0e25\u0e14\u0e34\u0e08\u0e34\u0e17\u0e31\u0e25 (\u0e2d\u0e07\u0e04\u0e4c\u0e01\u0e23\u0e21\u0e2b\u0e32\u0e0a\u0e19) (\u0e2a\u0e1e\u0e23.) \u0e2d\u0e32\u0e04\u0e32\u0e23\u0e2a\u0e16\u0e32\u0e1a\u0e31\u0e19\u0e40\u0e1e\u0e37\u0e48\u0e2d\u0e01\u0e32\u0e23\u0e1a\u0e38\u0e15\u0e34\u0e18\u0e23\u0e23\u0e21\u0e41\u0e2b\u0e48\u0e07\u0e1b\u0e23\u0e30\u0e40\u0e17\u0e28\u0e44\u0e17\u0e22 (TIJ)\n\u0e0a\u0e31\u0e49\u0e19 4 \u0e40\u0e25\u0e02\u0e17\u0e35\u0e48 999 \u0e16\u0e19\u0e19\u0e41\u0e08\u0e49\u0e07\u0e27\u0e31\u0e12\u0e19\u0e30 \u0e41\u0e02\u0e27\u0e07\u0e17\u0e38\u0e48\u0e07\u0e2a\u0e2d\u0e07\u0e2b\u0e49\u0e2d\u0e07 \u0e40\u0e02\u0e15\u0e2b\u0e25\u0e31\u0e01\u0e2a\u0e35\u0e48 \u0e01\u0e23\u0e38\u0e07\u0e40\u0e17\u0e1e\u0e2f 10210","header_size":"p","typography_typography":"custom","typography_font_size":{"unit":"em","size":1,"sizes":[]},"typography_font_size_tablet":{"unit":"em","size":"","sizes":[]},"typography_font_size_mobile":{"unit":"em","size":"","sizes":[]},"typography_font_weight":"500","typography_line_height":{"unit":"em","size":1.5,"sizes":[]}},"elements":[],"isInner":false,"widgetType":"heading","elType":"widget"}],"isInner":true,"elType":"container"}],"isInner":false,"elType":"container"},{"id":"7db4d28c","settings":{"flex_direction":"column","background_background":"classic","margin":{"unit":"px","top":"0","right":"0","bottom":"100","left":"0","isLinked":false},"padding":{"unit":"px","top":"0","right":"0","bottom":"0","left":"0","isLinked":false}},"elements":[{"id":"1dbe196b","settings":{"image":{"id":5311,"url":"https:\/\/standard.wpdevs.co\/wp-content\/uploads\/2025\/05\/about-banner-3.webp"},"_margin":{"unit":"px","top":"0","right":"0","bottom":"-19","left":"0","isLinked":false}},"elements":[],"isInner":false,"widgetType":"image","elType":"widget"},{"id":"7885cb69","settings":{"content_width":"full","background_background":"classic","background_color":"#4347A41C","border_radius":{"unit":"px","top":"30","right":"30","bottom":"30","left":"30","isLinked":true},"margin":{"unit":"px","top":"0","right":"0","bottom":"0","left":"0","isLinked":true},"_flex_align_self":"center","padding":{"unit":"px","top":"30","right":"30","bottom":"30","left":"30","isLinked":true}},"elements":[{"id":"50dc69bb","settings":{"presetTitle":"Container","presetIcon":"eicon-container","content_width":"full","min_height":{"unit":"px","size":0,"sizes":[]},"grid_columns_grid":{"unit":"fr","size":1,"sizes":[]},"grid_rows_grid":{"unit":"fr","size":1,"sizes":[]},"grid_rows_grid_tablet":{"unit":"custom","size":"","sizes":[]},"grid_rows_grid_mobile":{"unit":"custom","size":"","sizes":[]},"grid_gaps":{"column":"0","row":"0","isLinked":false,"unit":"px"},"flex_direction":"column","flex_gap":{"column":"0","row":"5","isLinked":false,"unit":"px","size":0},"margin":{"unit":"px","top":"0","right":"0","bottom":"0","left":"0","isLinked":false},"padding":{"unit":"px","top":"0","right":"0","bottom":"0","left":"0","isLinked":false},"_flex_align_self":"center"},"elements":[{"id":"2a51200","settings":{"title":"\u0e1d\u0e48\u0e32\u0e22\u0e21\u0e32\u0e15\u0e23\u0e10\u0e32\u0e19\u0e14\u0e34\u0e08\u0e34\u0e17\u0e31\u0e25\u0e20\u0e32\u0e04\u0e23\u0e31\u0e10","header_size":"h1","typography_typography":"custom","typography_font_size_mobile":{"unit":"em","size":1.5,"sizes":[]},"_flex_align_self":"center"},"elements":[],"isInner":false,"widgetType":"heading","elType":"widget"},{"id":"6f34ed59","settings":{"title":"\u0e1d\u0e48\u0e32\u0e22\u0e21\u0e32\u0e15\u0e23\u0e10\u0e32\u0e19\u0e14\u0e34\u0e08\u0e34\u0e17\u0e31\u0e25\u0e20\u0e32\u0e04\u0e23\u0e31\u0e10","header_size":"h1","typography_typography":"custom","typography_font_size":{"unit":"em","size":2,"sizes":[]},"typography_font_size_tablet":{"unit":"em","size":"","sizes":[]},"typography_font_size_mobile":{"unit":"em","size":1,"sizes":[]},"_margin":{"unit":"px","top":"0","right":"0","bottom":"20","left":"0","isLinked":false},"_padding":{"unit":"px","top":"0","right":"0","bottom":"0","left":"0","isLinked":false},"_flex_align_self":"center"},"elements":[],"isInner":false,"widgetType":"heading","elType":"widget"},{"id":"53e1a468","settings":{"title":"\u0e2a\u0e33\u0e19\u0e31\u0e01\u0e07\u0e32\u0e19\u0e1e\u0e31\u0e12\u0e19\u0e32\u0e23\u0e31\u0e10\u0e1a\u0e32\u0e25\u0e14\u0e34\u0e08\u0e34\u0e17\u0e31\u0e25 (\u0e2d\u0e07\u0e04\u0e4c\u0e01\u0e32\u0e23\u0e21\u0e2b\u0e32\u0e0a\u0e19) (\u0e2a\u0e1e\u0e23.)","align_mobile":"center","typography_typography":"custom","typography_font_size":{"unit":"em","size":1,"sizes":[]},"typography_font_size_tablet":{"unit":"em","size":"","sizes":[]},"typography_font_size_mobile":{"unit":"em","size":1,"sizes":[]},"_flex_align_self":"center"},"elements":[],"isInner":false,"widgetType":"heading","elType":"widget"},{"id":"4bbd4258","settings":{"title":"Digital Government Development Agency (Public Organization) (DGA)","align_mobile":"center","typography_typography":"custom","typography_font_size":{"unit":"em","size":1,"sizes":[]},"typography_font_size_tablet":{"unit":"em","size":"","sizes":[]},"typography_font_size_mobile":{"unit":"em","size":"","sizes":[]},"_flex_align_self":"center"},"elements":[],"isInner":false,"widgetType":"heading","elType":"widget"}],"isInner":true,"elType":"container"},{"id":"7ba42d2c","settings":{"content_width":"full","flex_direction":"row","flex_justify_content":"center"},"elements":[{"id":"dc1c87b","settings":{"selected_icon":{"value":"far fa-clock","library":"fa-regular"},"title_text":"\u0e40\u0e27\u0e25\u0e32\u0e17\u0e33\u0e01\u0e32\u0e23","description_text":"\u0e27\u0e31\u0e19\u0e08\u0e31\u0e19\u0e17\u0e23\u0e4c \u0e16\u0e36\u0e07 \u0e27\u0e31\u0e19\u0e28\u0e38\u0e01\u0e23\u0e4c \u0e40\u0e27\u0e25\u0e32 <br>08.30 \u2013 17.30 \u0e19.","_element_width":"initial","_element_custom_width":{"unit":"px","size":250,"sizes":[]}},"elements":[],"isInner":false,"widgetType":"icon-box","elType":"widget"},{"id":"7e77a98e","settings":{"selected_icon":{"value":"fas fa-map-marker-alt","library":"fa-solid"},"title_text":"\u0e2a\u0e16\u0e32\u0e19\u0e17\u0e35\u0e48\u0e15\u0e31\u0e49\u0e07\u0e1d\u0e48\u0e32\u0e22\u0e21\u0e32\u0e15\u0e23\u0e10\u0e32\u0e19\u0e14\u0e34\u0e08\u0e34\u0e17\u0e31\u0e25\u0e20\u0e32\u0e04\u0e23\u0e31\u0e10","description_text":"\u0e2d\u0e32\u0e04\u0e32\u0e23\u0e2a\u0e16\u0e32\u0e1a\u0e31\u0e19\u0e40\u0e1e\u0e37\u0e48\u0e2d\u0e01\u0e32\u0e23\u0e22\u0e38\u0e15\u0e34\u0e18\u0e23\u0e23\u0e21\u0e41\u0e2b\u0e48\u0e07\u0e1b\u0e23\u0e30\u0e40\u0e17\u0e28\u0e44\u0e17\u0e22 (TIJ) \u0e0a\u0e31\u0e49\u0e19 4 \u0e40\u0e25\u0e02\u0e17\u0e35\u0e48 999 \u0e16\u0e19\u0e19\u0e41\u0e08\u0e49\u0e07\u0e27\u0e31\u0e12\u0e19\u0e30 \u0e41\u0e02\u0e27\u0e07\u0e17\u0e38\u0e48\u0e07\u0e2a\u0e2d\u0e07\u0e2b\u0e49\u0e2d\u0e07 \u0e40\u0e02\u0e15\u0e2b\u0e25\u0e31\u0e01\u0e2a\u0e35\u0e48 \u0e01\u0e23\u0e38\u0e07\u0e40\u0e17\u0e1e\u0e2f 10210","_element_width":"initial","_element_custom_width":{"unit":"px","size":250,"sizes":[]}},"elements":[],"isInner":false,"widgetType":"icon-box","elType":"widget"},{"id":"1a1bf303","settings":{"selected_icon":{"value":"fas fa-phone-alt","library":"fa-solid"},"title_text":"\u0e40\u0e1a\u0e2d\u0e23\u0e4c\u0e15\u0e34\u0e14\u0e15\u0e48\u0e2d","description_text":"\u0e42\u0e17\u0e23\u0e28\u0e31\u0e1e\u0e17\u0e4c (+66) 0 2612 6000<br>\nContact Center (+66) 0 2612 6060<br>\n\u0e42\u0e17\u0e23\u0e2a\u0e32\u0e23 (+66) 0 2612 6011 \/ (+66) 0 2612 6012","_element_width":"initial","_element_custom_width":{"unit":"px","size":250,"sizes":[]}},"elements":[],"isInner":false,"widgetType":"icon-box","elType":"widget"},{"id":"7e4c8673","settings":{"selected_icon":{"value":"fas fa-mail-bulk","library":"fa-solid"},"title_text":"\u0e2d\u0e35\u0e40\u0e21\u0e25","description_text":"contact@dga.or.th","_element_width":"initial","_element_custom_width":{"unit":"px","size":250,"sizes":[]}},"elements":[],"isInner":false,"widgetType":"icon-box","elType":"widget"}],"isInner":true,"elType":"container"}],"isInner":true,"elType":"container"}],"isInner":false,"elType":"container"}],"page_settings":[],"version":"0.4","title":"Contact-002","type":"page"}